awesome_rasam/__init__.py
awesome_rasam-0.0.6.dist-info/LICENSE
awesome_rasam-0.0.6.dist-info/METADATA
awesome_rasam-0.0.6.dist-info/WHEEL
awesome_rasam-0.0.6.dist-info/top_level.txt
awesome_rasam-0.0.6.dist-info/RECORD
